[
    {
      "image_url": "https://images.unsplash.com/photo-1572449043416-55f4685c9bb7?ixid=MnwxMjA3fDB8MHxwaG90by1wYWdlfHx8fGVufDB8fHx8&ixlib=rb-1.2.1&auto=format&fit=crop&w=2080&q=80",
      "owner": "Salad Lover",
      "description": "Look at this green machine!"
    },
    {
      "image_url": "https://images.unsplash.com/photo-1543826173-70651703c5a4?ixid=MnwxMjA3fDB8MHxwaG90by1wYWdlfHx8fGVufDB8fHx8&ixlib=rb-1.2.1&auto=format&fit=crop&w=1158&q=80",
      "owner": "The Fancy Foodie",
      "description": "Plated perfection 🥰"
    },
    {
      "image_url": "https://images.unsplash.com/photo-1546069901-ba9599a7e63c?ixid=MnwxMjA3fDB8MHxwaG90by1wYWdlfHx8fGVufDB8fHx8&ixlib=rb-1.2.1&auto=format&fit=crop&w=1160&q=80",
      "owner": "The Fancy Foodie",
      "description": "Poke box anyone?"
    },
    {
      "image_url": "https://images.unsplash.com/photo-1595475177190-04a1111e5119?ixid=MnwxMjA3fDB8MHxwaG90by1wYWdlfHx8fGVufDB8fHx8&ixlib=rb-1.2.1&auto=format&fit=crop&w=1160&q=80",
      "owner": "Dr Foodie",
      "description": "Breakfast of champions"
    },
    {
      "image_url": "https://images.unsplash.com/photo-1554886729-1a57f2750570?ixid=MnwxMjA3fDB8MHxwaG90by1wYWdlfHx8fGVufDB8fHx8&ixlib=rb-1.2.1&auto=format&fit=crop&w=1160&q=80",
      "owner": "Wake and Bake",
      "description": "Who could say no to icing on anything"
    },
    {
      "image_url": "https://images.unsplash.com/photo-1447195047884-0f014b0d9288?ixid=MnwxMjA3fDB8MHxwaG90by1wYWdlfHx8fGVufDB8fHx8&ixlib=rb-1.2.1&auto=format&fit=crop&w=1160&q=80",
      "owner": "Chocolate on Chocolate",
      "description": "My happy place"
    },
    {
      "image_url": "https://images.unsplash.com/photo-1569718212165-3a8278d5f624?ixid=MnwxMjA3fDB8MHxwaG90by1wYWdlfHx8fGVufDB8fHx8&ixlib=rb-1.2.1&auto=format&fit=crop&w=1160&q=80",
      "owner": "Ramen Roy",
      "description": "Prawns and Eggs.... yes please"
    },
    {
      "image_url": "https://images.unsplash.com/photo-1605851868183-7a4de52117fa?ixid=MnwxMjA3fDB8MHxwaG90by1wYWdlfHx8fGVufDB8fHx8&ixlib=rb-1.2.1&auto=format&fit=crop&w=1160&q=80",
      "owner": "Noodle Nerd",
      "description": "Look at the size of those noodles!!"
    }
  ]
  